util_collection/__init__.py
util_collection/doc_util/__init__.py
util_collection/doc_util/count_pages.py
util_collection-0.1.4.dist-info/METADATA
util_collection-0.1.4.dist-info/WHEEL
util_collection-0.1.4.dist-info/top_level.txt
util_collection-0.1.4.dist-info/RECORD
