Metadata-Version: 2.1
Name: util_collection
Version: 0.1.4
Summary: Some util function
Classifier: Programming Language :: Python :: 3
Classifier: License :: OSI Approved :: MIT License
Classifier: Operating System :: OS Independent
Requires-Python: >=3.7
